forge_python/__init__.py
forge_python/forge.py
forge_python/metrics/__init__.py
forge_python/metrics/economics.py
forge_python-0.0.12.1.dist-info/METADATA
forge_python-0.0.12.1.dist-info/WHEEL
forge_python-0.0.12.1.dist-info/licenses/LICENSE
forge_python-0.0.12.1.dist-info/RECORD
